{
  "version": 3,
  "overallClassification": {
    "banner": "UNCLASSIFIED//REL TO USA, AUS, CAN, GBR, NZL",
    "classification": "U",
    "ownerProducer": [
      "USA"
    ],
    "releaseableTo": [
      "USA",
      "AUS",
      "CAN",
      "GBR",
      "NZL"
    ],
    "disseminationControls": [
      "REL"
    ]
  },
  "id": "23456789-aaaa-bbbb-nnnn-nopqrstuvwxy",
  "name": "Hidden Leaf Village Command Center 1",
  "createdDate": 1720065600,
  "lastUpdatedDate": 1737217365,
  "excerciseIndicator": "gide-12345678",
  "equipment": [
    {
      "midbEquipmentCode": {
        "value": "L9ASQ",
        "ism": {
          "banner": "UNCLASSIFIED//REL TO USA, AUS, CAN, GBR, NZL",
          "classification": "U",
          "ownerProducer": [
            "USA"
          ],
          "releaseableTo": [
            "USA",
            "AUS",
            "CAN",
            "GBR",
            "NZL"
          ],
          "disseminationControls": [
            "REL"
          ]
        }
      },
      "condition": {
        "value": "RDY",
        "ism": {
          "banner": "UNCLASSIFIED//REL TO USA, AUS, CAN, GBR, NZL",
          "classification": "U",
          "ownerProducer": [
            "USA"
          ],
          "releaseableTo": [
            "USA",
            "AUS",
            "CAN",
            "GBR",
            "NZL"
          ],
          "disseminationControls": [
            "REL"
          ]
        }
      }
    }
  ],
  "unit": {
    "id": {
      "value": "DFGCH01256",
      "ism": {
        "banner": "UNCLASSIFIED//REL TO USA, AUS, CAN, GBR, NZL",
        "classification": "U",
        "ownerProducer": [
          "USA"
        ],
        "releaseableTo": [
          "USA",
          "AUS",
          "CAN",
          "GBR",
          "NZL"
        ],
        "disseminationControls": [
          "REL"
        ]
      }
    }
  },
  "ontology": {
    "affiliation": {
      "value": "F",
      "ism": {
        "banner": "UNCLASSIFIED//REL TO USA, AUS, CAN, GBR, NZL",
        "classification": "U",
        "ownerProducer": [
          "USA"
        ],
        "releaseableTo": [
          "USA",
          "AUS",
          "CAN",
          "GBR",
          "NZL"
        ],
        "disseminationControls": [
          "REL"
        ]
      }
    },
    "nationality": {
      "value": "JP",
      "ism": {
        "banner": "UNCLASSIFIED//REL TO USA, AUS, CAN, GBR, NZL",
        "classification": "U",
        "ownerProducer": [
          "USA"
        ],
        "releaseableTo": [
          "USA",
          "AUS",
          "CAN",
          "GBR",
          "NZL"
        ],
        "disseminationControls": [
          "REL"
        ]
      }
    },
    "domain": {
      "value": "GROUND",
      "ism": {
        "banner": "SECRET//REL TO USA, AUS, CAN, GBR, NZL",
        "classification": "S",
        "ownerProducer": [
          "USA"
        ],
        "releaseableTo": [
          "USA",
          "AUS",
          "CAN",
          "GBR",
          "NZL"
        ],
        "disseminationControls": [
          "REL"
        ]
      }
    },
    "allegience": {
      "value": "JAP",
      "ism": {
        "banner": "SECRET//REL TO USA, AUS, CAN, GBR, NZL",
        "classification": "S",
        "ownerProducer": [
          "USA"
        ],
        "releaseableTo": [
          "USA",
          "AUS",
          "CAN",
          "GBR",
          "NZL"
        ],
        "disseminationControls": [
          "REL"
        ]
      }
    },
    "coi": {
      "value": "INDOPACOM",
      "ism": {
        "banner": "SECRET//REL TO USA, AUS, CAN, GBR, NZL",
        "classification": "S",
        "ownerProducer": [
          "USA"
        ],
        "releaseableTo": [
          "USA",
          "AUS",
          "CAN",
          "GBR",
          "NZL"
        ],
        "disseminationControls": [
          "REL"
        ]
      }
    }
  },
  "facility": {
    "facilitySurrogateKey": {
      "value": "20002000704933",
      "ism": {
        "banner": "UNCLASSIFIED//REL TO USA, AUS, CAN, GBR, NZL",
        "classification": "U",
        "ownerProducer": [
          "USA"
        ],
        "releaseableTo": [
          "USA",
          "AUS",
          "CAN",
          "GBR",
          "NZL"
        ],
        "disseminationControls": [
          "REL"
        ]
      }
    },
    "facilityId": {
      "value": "20845",
      "ism": {
        "banner": "UNCLASSIFIED//REL TO USA, AUS, CAN, GBR, NZL",
        "classification": "U",
        "ownerProducer": [
          "USA"
        ],
        "releaseableTo": [
          "USA",
          "AUS",
          "CAN",
          "GBR",
          "NZL"
        ],
        "disseminationControls": [
          "REL"
        ]
      }
    },
    "facilityName": {
      "value": "Hidden Leaf Village Command Center 1",
      "ism": {
        "banner": "SECRET//REL TO USA, AUS, CAN, GBR, NZL",
        "classification": "S",
        "ownerProducer": [
          "USA"
        ],
        "releaseableTo": [
          "USA",
          "AUS",
          "CAN",
          "GBR",
          "NZL"
        ],
        "disseminationControls": [
          "REL"
        ]
      }
    }
  },
  "provenance": [
    {
      "id": {
        "value": "oms-23456789",
        "ism": {
          "banner": "SECRET//REL TO USA, AUS, CAN, GBR, NZL",
          "classification": "S",
          "ownerProducer": [
            "USA"
          ],
          "releaseableTo": [
            "USA",
            "AUS",
            "CAN",
            "GBR",
            "NZL"
          ],
          "disseminationControls": [
            "REL"
          ]
        }
      }
    }
  ],
  "operationalStatus": {
    "value": "OPR",
    "ism": {
      "banner": "UNCLASSIFIED//REL TO USA, AUS, CAN, GBR, NZL",
      "classification": "U",
      "ownerProducer": [
        "USA"
      ],
      "releaseableTo": [
        "USA",
        "AUS",
        "CAN",
        "GBR",
        "NZL"
      ],
      "disseminationControls": [
        "REL"
      ]
    }
  },
  "functionalRole": {
    "value": "COM",
    "ism": {
      "banner": "UNCLASSIFIED//REL TO USA, AUS, CAN, GBR, NZL",
      "classification": "U",
      "ownerProducer": [
        "USA"
      ],
      "releaseableTo": [
        "USA",
        "AUS",
        "CAN",
        "GBR",
        "NZL"
      ],
      "disseminationControls": [
        "REL"
      ]
    }
  }
}